illallangi/data/mastodon/__init__.py
illallangi/data/mastodon/__version__.py
illallangi/data/mastodon/apps.py
illallangi/data/mastodon/adapters/__init__.py
illallangi/data/mastodon/adapters/mastodon.py
illallangi/data/mastodon/admin/__init__.py
illallangi/data/mastodon/admin/status.py
illallangi/data/mastodon/checks/__init__.py
illallangi/data/mastodon/checks/mastodon.py
illallangi/data/mastodon/diffsyncmodels/__init__.py
illallangi/data/mastodon/diffsyncmodels/status.py
illallangi/data/mastodon/migrations/0001_initial.py
illallangi/data/mastodon/migrations/__init__.py
illallangi/data/mastodon/models/__init__.py
illallangi/data/mastodon/models/status.py
illallangi/data/mastodon/static/mastodon/statuses.png
illallangi/data/mastodon/templates/mastodon/status_detail.html
illallangi/data/mastodon/templates/mastodon/status_list.html
illallangi/data/mastodon/views/__init__.py
illallangi/data/mastodon/views/status_detail.py
illallangi/data/mastodon/views/status_list.py
illallangi_data_mastodon-0.5.0.dist-info/METADATA
illallangi_data_mastodon-0.5.0.dist-info/WHEEL
illallangi_data_mastodon-0.5.0.dist-info/entry_points.txt
illallangi_data_mastodon-0.5.0.dist-info/licenses/LICENSE
illallangi_data_mastodon-0.5.0.dist-info/RECORD
